scryfall_cache/__init__.py
scryfall_cache/scryfall_cache.py
scryfall_cache-0.2.2.dist-info/AUTHORS.md
scryfall_cache-0.2.2.dist-info/LICENSE
scryfall_cache-0.2.2.dist-info/METADATA
scryfall_cache-0.2.2.dist-info/WHEEL
scryfall_cache-0.2.2.dist-info/top_level.txt
scryfall_cache-0.2.2.dist-info/RECORD
