Metadata-Version: 2.1
Name: scryfall-cache
Version: 0.2.2
Summary: Scryfall Cache is a library which minimizes the number of requests made to the Scryfall API.
Home-page: https://github.com/cmeister2/scryfall_cache
Author: Max Dymond
Author-email: cmeister2@gmail.com
License: MIT license
Keywords: scryfall_cache
Platform: UNKNOWN
Classifier: Development Status :: 2 - Pre-Alpha
Classifier: Intended Audience :: Developers
Classifier: License :: OSI Approved :: MIT License
Classifier: Natural Language :: English
Classifier: Programming Language :: Python :: 2
Classifier: Programming Language :: Python :: 2.7
Classifier: Programming Language :: Python :: 3
Classifier: Programming Language :: Python :: 3.4
Classifier: Programming Language :: Python :: 3.5
Classifier: Programming Language :: Python :: 3.6
Classifier: Programming Language :: Python :: 3.7
Requires-Dist: requests
Requires-Dist: requests-ratelimit-adapter
Requires-Dist: appdirs
Requires-Dist: pony
